Metadata-Version: 2.1
Name: ezy-cli
Version: 1.0.0
Summary: A CLI tool that manages files and directories.
Home-page: https://github.com/ayoub-aberbach/ez_cli
Author: Ayoub A.
Author-email: aberbach.me@gmail.com
Classifier: Programming Language :: Python :: 3
Classifier: License :: OSI Approved :: MIT License
Classifier: Operating System :: OS Independent
Requires-Python: >=3.6
